pycolour/__init__.py
pycolour-1.0.3.dist-info/LICENSE
pycolour-1.0.3.dist-info/METADATA
pycolour-1.0.3.dist-info/WHEEL
pycolour-1.0.3.dist-info/top_level.txt
pycolour-1.0.3.dist-info/RECORD
