Metadata-Version: 2.1
Name: pycolour
Version: 1.0.3
Summary: A simple command line colour tool for python
Home-page: https://github.com/PythonEuropa/pycolour
Author: Daniel Smith
Author-email: daniel@waiora.com.au
License: UNKNOWN
Platform: UNKNOWN
Classifier: Programming Language :: Python :: 3
Classifier: License :: OSI Approved :: MIT License
Classifier: Operating System :: OS Independent
Requires-Python: >=3.6
